seureco_tools/Cls_CitationsProcessor_v0_3.py
seureco_tools/Cls_IdentityGenerator_v0_4.py
seureco_tools/Mod_GeneralUtilities.py
seureco_tools/Mod_PatentsFamiliesAndCitationValuesAggregatedOnTechs.py
seureco_tools/Mod_RdAndCitationsDataForIODE.py
seureco_tools/Mod_UtilitiesForGUI.py
seureco_tools/Mod_UtilitiesForIODE.py
seureco_tools/Run_CitationsProcessor_v1.py
seureco_tools/Run_IdentityGenerator_v1.py
seureco_tools/__init__.py
seureco_tools-0.1.0.dist-info/METADATA
seureco_tools-0.1.0.dist-info/WHEEL
seureco_tools-0.1.0.dist-info/top_level.txt
seureco_tools-0.1.0.dist-info/RECORD
