Metadata-Version: 2.4
Name: seureco_tools
Version: 0.1.0
Summary: IODE package for data preprocessing
Author: Hajar
Author-email: hajar.sriri@etu.univ-paris1.fr
Requires-Python: >=3.8
Requires-Dist: pandas
Requires-Dist: numpy
Dynamic: author
Dynamic: author-email
Dynamic: requires-dist
Dynamic: requires-python
Dynamic: summary
